README.md
setup.cfg
setup.py
credit_card_clients_model/__init__.py
credit_card_clients_model/context.py
credit_card_clients_model/pipeline.py
credit_card_clients_model/preprocessors.py
credit_card_clients_model/train.py
credit_card_clients_model.egg-info/PKG-INFO
credit_card_clients_model.egg-info/SOURCES.txt
credit_card_clients_model.egg-info/dependency_links.txt
credit_card_clients_model.egg-info/top_level.txt
credit_card_clients_model/config/__init__.py
credit_card_clients_model/config/config.py