Metadata-Version: 2.1
Name: credit-card-clients-model
Version: 1.0.4
Summary: credit card clients model
Home-page: UNKNOWN
Author: Matthew Aguerreberry
License: UNKNOWN
Platform: UNKNOWN
Requires-Python: >=3.7
